pixelarraylib/__init__.py
pixelarraylib/__main__.py
pixelarraylib/aliyun/__init__.py
pixelarraylib/aliyun/acr.py
pixelarraylib/aliyun/aliyun_email.py
pixelarraylib/aliyun/billing.py
pixelarraylib/aliyun/content_scanner.py
pixelarraylib/aliyun/domain.py
pixelarraylib/aliyun/eci.py
pixelarraylib/aliyun/ecs.py
pixelarraylib/aliyun/eip.py
pixelarraylib/aliyun/fc.py
pixelarraylib/aliyun/oss.py
pixelarraylib/aliyun/polardb.py
pixelarraylib/aliyun/sms.py
pixelarraylib/aliyun/sts.py
pixelarraylib/db_utils/mysql.py
pixelarraylib/db_utils/redis.py
pixelarraylib/decorators/__init__.py
pixelarraylib/decorators/decorators.py
pixelarraylib/gitlab/__init__.py
pixelarraylib/gitlab/code_analyzer.py
pixelarraylib/gitlab/pypi_package_manager.py
pixelarraylib/monitor/__init__.py
pixelarraylib/monitor/feishu.py
pixelarraylib/scripts/__init__.py
pixelarraylib/scripts/build_website.py
pixelarraylib/scripts/collect_code_to_txt.py
pixelarraylib/scripts/create_test_case_files.py
pixelarraylib/scripts/nginx_proxy_to_ecs.py
pixelarraylib/scripts/remove_empty_lines.py
pixelarraylib/scripts/tson_convert.py
pixelarraylib/system/__init__.py
pixelarraylib/system/common.py
pixelarraylib/system/cron_manager.py
pixelarraylib/system/tson.py
pixelarraylib/utils/name_generator.py
pixelarraylib-1.2.2.dist-info/licenses/LICENSE
pixelarraylib-1.2.2.dist-info/METADATA
pixelarraylib-1.2.2.dist-info/WHEEL
pixelarraylib-1.2.2.dist-info/entry_points.txt
pixelarraylib-1.2.2.dist-info/top_level.txt
pixelarraylib-1.2.2.dist-info/RECORD
