Metadata-Version: 2.4
Name: pixelarraylib
Version: 1.2.2
Summary: PixelArray Python开发工具库 - 包含阿里云服务、数据库工具、装饰器、监控等功能
Author-email: Lu qi <qi.lu@pixelarrayai.com>
License-Expression: MIT
Project-URL: Homepage, https://gitlab.com/pixelarrayai/general_pythondevutils_lib
Project-URL: Bug Reports, https://gitlab.com/pixelarrayai/general_pythondevutils_lib/-/issues
Project-URL: Source, https://gitlab.com/pixelarrayai/general_pythondevutils_lib
Keywords: python,utils,aliyun,database,tools,pixelarray
Classifier: Development Status :: 4 - Beta
Classifier: Intended Audience :: Developers
Classifier: Operating System :: OS Independent
Classifier: Programming Language :: Python :: 3
Classifier: Programming Language :: Python :: 3.8
Classifier: Programming Language :: Python :: 3.9
Classifier: Programming Language :: Python :: 3.10
Classifier: Programming Language :: Python :: 3.11
Classifier: Programming Language :: Python :: 3.12
Classifier: Programming Language :: Python :: 3.13
Classifier: Topic :: Software Development :: Libraries :: Python Modules
Classifier: Topic :: Utilities
Requires-Python: >=3.8
License-File: LICENSE
Provides-Extra: monitor
Requires-Dist: requests; extra == "monitor"
Provides-Extra: system
Requires-Dist: cryptography; extra == "system"
Requires-Dist: paramiko; extra == "system"
Requires-Dist: requests; extra == "system"
Provides-Extra: utils
Requires-Dist: names; extra == "utils"
Requires-Dist: Faker; extra == "utils"
Provides-Extra: mysql
Requires-Dist: pymysql; extra == "mysql"
Requires-Dist: aiomysql; extra == "mysql"
Requires-Dist: requests; extra == "mysql"
Provides-Extra: redis
Requires-Dist: redis; extra == "redis"
Requires-Dist: requests; extra == "redis"
Provides-Extra: gitlab
Requires-Dist: requests; extra == "gitlab"
Requires-Dist: aiohttp; extra == "gitlab"
Requires-Dist: pandas; extra == "gitlab"
Provides-Extra: aliyun-oss
Requires-Dist: oss2; extra == "aliyun-oss"
Requires-Dist: aiohttp; extra == "aliyun-oss"
Requires-Dist: aiofiles; extra == "aliyun-oss"
Requires-Dist: requests; extra == "aliyun-oss"
Requires-Dist: cryptography; extra == "aliyun-oss"
Requires-Dist: paramiko; extra == "aliyun-oss"
Provides-Extra: aliyun-sts
Requires-Dist: alibabacloud_sts20150401; extra == "aliyun-sts"
Requires-Dist: alibabacloud_tea_openapi; extra == "aliyun-sts"
Requires-Dist: alibabacloud_tea_util; extra == "aliyun-sts"
Requires-Dist: oss2; extra == "aliyun-sts"
Requires-Dist: requests; extra == "aliyun-sts"
Requires-Dist: redis; extra == "aliyun-sts"
Provides-Extra: aliyun-sms
Requires-Dist: alibabacloud_dysmsapi20170525; extra == "aliyun-sms"
Requires-Dist: alibabacloud_tea_openapi; extra == "aliyun-sms"
Requires-Dist: alibabacloud_tea_util; extra == "aliyun-sms"
Requires-Dist: requests; extra == "aliyun-sms"
Provides-Extra: aliyun-email
Requires-Dist: alibabacloud_dm20151123; extra == "aliyun-email"
Requires-Dist: alibabacloud_tea_openapi; extra == "aliyun-email"
Requires-Dist: alibabacloud_tea_util; extra == "aliyun-email"
Requires-Dist: requests; extra == "aliyun-email"
Provides-Extra: aliyun-content-scanner
Requires-Dist: alibabacloud_green20220302; extra == "aliyun-content-scanner"
Requires-Dist: alibabacloud_tea_openapi; extra == "aliyun-content-scanner"
Requires-Dist: alibabacloud_tea_util; extra == "aliyun-content-scanner"
Requires-Dist: requests; extra == "aliyun-content-scanner"
Provides-Extra: aliyun-domain
Requires-Dist: alibabacloud_alidns20150109; extra == "aliyun-domain"
Requires-Dist: alibabacloud_tea_openapi; extra == "aliyun-domain"
Requires-Dist: alibabacloud_tea_util; extra == "aliyun-domain"
Provides-Extra: aliyun-acr
Requires-Dist: alibabacloud_cr20181201; extra == "aliyun-acr"
Requires-Dist: alibabacloud_credentials; extra == "aliyun-acr"
Requires-Dist: alibabacloud_tea_openapi; extra == "aliyun-acr"
Requires-Dist: alibabacloud_tea_util; extra == "aliyun-acr"
Requires-Dist: requests; extra == "aliyun-acr"
Provides-Extra: aliyun-billing
Requires-Dist: alibabacloud_bssopenapi20171214; extra == "aliyun-billing"
Requires-Dist: alibabacloud_tea_openapi; extra == "aliyun-billing"
Requires-Dist: alibabacloud_tea_util; extra == "aliyun-billing"
Requires-Dist: pandas; extra == "aliyun-billing"
Requires-Dist: requests; extra == "aliyun-billing"
Provides-Extra: aliyun-ecs
Requires-Dist: alibabacloud_cms20190101; extra == "aliyun-ecs"
Requires-Dist: alibabacloud_tea_openapi; extra == "aliyun-ecs"
Requires-Dist: alibabacloud_tea_util; extra == "aliyun-ecs"
Provides-Extra: aliyun-eip
Requires-Dist: alibabacloud_vpc20160428; extra == "aliyun-eip"
Requires-Dist: alibabacloud_tea_openapi; extra == "aliyun-eip"
Requires-Dist: alibabacloud_tea_util; extra == "aliyun-eip"
Requires-Dist: requests; extra == "aliyun-eip"
Provides-Extra: aliyun-eci
Requires-Dist: alibabacloud_eci20180808; extra == "aliyun-eci"
Requires-Dist: alibabacloud_vpc20160428; extra == "aliyun-eci"
Requires-Dist: alibabacloud_tea_openapi; extra == "aliyun-eci"
Requires-Dist: alibabacloud_tea_util; extra == "aliyun-eci"
Requires-Dist: requests; extra == "aliyun-eci"
Provides-Extra: aliyun-fc
Requires-Dist: alibabacloud_fc20230330; extra == "aliyun-fc"
Requires-Dist: alibabacloud_darabonba_stream; extra == "aliyun-fc"
Requires-Dist: alibabacloud_tea_openapi; extra == "aliyun-fc"
Requires-Dist: alibabacloud_tea_util; extra == "aliyun-fc"
Requires-Dist: requests; extra == "aliyun-fc"
Requires-Dist: cryptography; extra == "aliyun-fc"
Requires-Dist: paramiko; extra == "aliyun-fc"
Provides-Extra: aliyun-polardb
Requires-Dist: alibabacloud_polardb20170801; extra == "aliyun-polardb"
Requires-Dist: alibabacloud_credentials; extra == "aliyun-polardb"
Requires-Dist: alibabacloud_tea_openapi; extra == "aliyun-polardb"
Requires-Dist: alibabacloud_tea_util; extra == "aliyun-polardb"
Requires-Dist: requests; extra == "aliyun-polardb"
Provides-Extra: aliyun
Requires-Dist: alibabacloud_tea_util; extra == "aliyun"
Requires-Dist: alibabacloud_cms20190101; extra == "aliyun"
Requires-Dist: alibabacloud_green20220302; extra == "aliyun"
Requires-Dist: alibabacloud_dm20151123; extra == "aliyun"
Requires-Dist: alibabacloud_fc20230330; extra == "aliyun"
Requires-Dist: alibabacloud_darabonba_stream; extra == "aliyun"
Requires-Dist: alibabacloud_dysmsapi20170525; extra == "aliyun"
Requires-Dist: alibabacloud_sts20150401; extra == "aliyun"
Requires-Dist: alibabacloud_alidns20150109; extra == "aliyun"
Requires-Dist: alibabacloud_eci20180808; extra == "aliyun"
Requires-Dist: alibabacloud_bssopenapi20171214; extra == "aliyun"
Requires-Dist: alibabacloud_cr20181201; extra == "aliyun"
Requires-Dist: alibabacloud_vpc20160428; extra == "aliyun"
Requires-Dist: alibabacloud_tea_openapi; extra == "aliyun"
Requires-Dist: alibabacloud_credentials; extra == "aliyun"
Requires-Dist: oss2; extra == "aliyun"
Requires-Dist: aiohttp; extra == "aliyun"
Requires-Dist: aiofiles; extra == "aliyun"
Requires-Dist: requests; extra == "aliyun"
Requires-Dist: cryptography; extra == "aliyun"
Requires-Dist: paramiko; extra == "aliyun"
Requires-Dist: redis; extra == "aliyun"
Requires-Dist: pandas; extra == "aliyun"
Provides-Extra: all
Requires-Dist: alibabacloud_tea_util; extra == "all"
Requires-Dist: alibabacloud_cms20190101; extra == "all"
Requires-Dist: alibabacloud_green20220302; extra == "all"
Requires-Dist: alibabacloud_dm20151123; extra == "all"
Requires-Dist: alibabacloud_fc20230330; extra == "all"
Requires-Dist: alibabacloud_darabonba_stream; extra == "all"
Requires-Dist: alibabacloud_dysmsapi20170525; extra == "all"
Requires-Dist: alibabacloud_sts20150401; extra == "all"
Requires-Dist: alibabacloud_alidns20150109; extra == "all"
Requires-Dist: alibabacloud_eci20180808; extra == "all"
Requires-Dist: alibabacloud_bssopenapi20171214; extra == "all"
Requires-Dist: alibabacloud_cr20181201; extra == "all"
Requires-Dist: alibabacloud_vpc20160428; extra == "all"
Requires-Dist: alibabacloud_tea_openapi; extra == "all"
Requires-Dist: alibabacloud_credentials; extra == "all"
Requires-Dist: alibabacloud_polardb20170801; extra == "all"
Requires-Dist: oss2; extra == "all"
Requires-Dist: pymysql; extra == "all"
Requires-Dist: aiomysql; extra == "all"
Requires-Dist: redis; extra == "all"
Requires-Dist: cryptography; extra == "all"
Requires-Dist: paramiko; extra == "all"
Requires-Dist: requests; extra == "all"
Requires-Dist: aiohttp; extra == "all"
Requires-Dist: aiofiles; extra == "all"
Requires-Dist: pandas; extra == "all"
Requires-Dist: names; extra == "all"
Requires-Dist: Faker; extra == "all"
Dynamic: license-file
